[{
	"plugin": {
		"api": {
			"class_name": "ZappAnalyticsPluginSwrve.ZappAnalyticsPluginSwrvePlugin"
		},
		"author_name": "Mohieddine Zarif",
		"author_email": "mohieddine.zarif@gotocme.com",
		"manifest_version": "0.0.9",
		"name": "ZappAnalyticsPluginSwrve",
		"description": "SportsMax Swrve Plugin Integration",
		"identifier": "ZappAnalyticsPluginSwrve",
		"type": "analytics",
		"platform": "ios",
		"min_zapp_sdk": "12.1.0",
		"whitelisted_account_ids": [
    		"5af949534da8f300080050f9"
  		],
		"dependency_repository_url": [],
		"dependency_name": "",
		"dependency_version": ""
	},
	"configuration_json": {}
}]
